dex_starr/__init__.py
dex_starr-0.0.1.dist-info/METADATA
dex_starr-0.0.1.dist-info/WHEEL
dex_starr-0.0.1.dist-info/entry_points.txt
dex_starr-0.0.1.dist-info/licenses/LICENSE.txt
dex_starr-0.0.1.dist-info/RECORD
