Metadata-Version: 2.1
Name: dex-starr
Version: 0.0.1
Summary: Unify and organize your comic collection.
Project-URL: Documentation, https://github.com/Buried-In-Code/Dex-Starr#readme
Project-URL: Homepage, https://pypi.org/project/Dex-Starr
Project-URL: Issues, https://github.com/Buried-In-Code/Dex-Starr/issues
Project-URL: Source, https://github.com/Buried-In-Code/Dex-Starr
Author-email: BuriedInCode <BuriedInCode@tuta.io>
License-File: LICENSE.txt
Keywords: comic,comics,metadata,tagger,tagging
Classifier: Development Status :: 4 - Beta
Classifier: Environment :: Console
Classifier: Intended Audience :: End Users/Desktop
Classifier: License :: OSI Approved :: GNU General Public License v3 or later (GPLv3+)
Classifier: Natural Language :: English
Classifier: Operating System :: MacOS
Classifier: Operating System :: Microsoft :: Windows
Classifier: Operating System :: POSIX :: Linux
Classifier: Programming Language :: Python
Classifier: Programming Language :: Python :: 3.8
Classifier: Programming Language :: Python :: 3.9
Classifier: Programming Language :: Python :: 3.10
Classifier: Programming Language :: Python :: 3.11
Classifier: Typing :: Typed
Requires-Python: >=3.8
Requires-Dist: esak>=1.3.2
Requires-Dist: himon>=0.3.0
Requires-Dist: mokkari>=2.3.3
Requires-Dist: natsort>=8.2.0
Requires-Dist: patool>=1.12
Requires-Dist: pydantic>=1.10.2
Requires-Dist: rich>=12.6.0
Requires-Dist: simyan>=0.12.0
Requires-Dist: tomli-w>=1.0.0
Requires-Dist: tomli>=2.0.1; python_version < '3.11'
Requires-Dist: xmltodict>=0.13.0
Provides-Extra: cb7
Requires-Dist: py7zr>=0.20.2; extra == 'cb7'
Provides-Extra: dev
Requires-Dist: pre-commit>=2.20.0; extra == 'dev'
